smfsb/__init__.py
smfsb/data.py
smfsb/inference.py
smfsb/models.py
smfsb/sim.py
smfsb/smfsbsbml.py
smfsb/spatial.py
smfsb/spn.py
smfsb-1.1.3.dist-info/METADATA
smfsb-1.1.3.dist-info/WHEEL
smfsb-1.1.3.dist-info/licenses/LICENSE
smfsb-1.1.3.dist-info/RECORD
