Metadata-Version: 2.4
Name: smfsb
Version: 1.1.3
Summary: Python code relating to the textbook, Stochastic modelling for systems biology, third edition
Project-URL: Homepage, https://github.com/darrenjw/python-smfsb
Project-URL: Documentation, https://python-smfsb.readthedocs.io/
Project-URL: Issues, https://github.com/darrenjw/python-smfsb/issues
Author-email: Darren Wilkinson <darrenjwilkinson@btinternet.com>
License-File: LICENSE
Classifier: License :: OSI Approved :: Apache Software License
Classifier: Operating System :: OS Independent
Classifier: Programming Language :: Python :: 3
Requires-Python: >=3.8
Requires-Dist: numpy>=2
Requires-Dist: sbmlsh
Requires-Dist: scipy
